neatprep/__init__.py
neatprep/cleaning.py
neatprep/encoding.py
neatprep/imputation.py
neatprep-0.1.0.dist-info/licenses/LICENSE
neatprep-0.1.0.dist-info/METADATA
neatprep-0.1.0.dist-info/WHEEL
neatprep-0.1.0.dist-info/top_level.txt
neatprep-0.1.0.dist-info/RECORD
